llama_index/postprocessor/sbert_rerank/__init__.py
llama_index/postprocessor/sbert_rerank/base.py
llama_index_postprocessor_sbert_rerank-0.4.2.dist-info/METADATA
llama_index_postprocessor_sbert_rerank-0.4.2.dist-info/WHEEL
llama_index_postprocessor_sbert_rerank-0.4.2.dist-info/licenses/LICENSE
llama_index_postprocessor_sbert_rerank-0.4.2.dist-info/RECORD
